quiz_game/__init__.py
quiz_game-0.0.3.dist-info/METADATA
quiz_game-0.0.3.dist-info/WHEEL
quiz_game-0.0.3.dist-info/licenses/LICENSE
quiz_game-0.0.3.dist-info/RECORD
