Metadata-Version: 2.4
Name: quiz_game
Version: 0.0.3
Summary: create a test in order to practice for exams, test your knowledge, and boost your memory!
Project-URL: Homepage, https://github.com/Alex0424/quiz
Project-URL: Issues, https://github.com/Alex0424/quiz
Author-email: Alexander Lindholm <lindholmalex.la@gmail.com>
License-File: LICENSE
Classifier: License :: OSI Approved :: MIT License
Classifier: Operating System :: OS Independent
Classifier: Programming Language :: Python :: 3
Requires-Python: >=3.0
